ambient_backend_api_client/__init__.py
ambient_backend_api_client/api_client.py
ambient_backend_api_client/api_response.py
ambient_backend_api_client/configuration.py
ambient_backend_api_client/exceptions.py
ambient_backend_api_client/py.typed
ambient_backend_api_client/rest.py
ambient_backend_api_client/api/__init__.py
ambient_backend_api_client/api/auth_api.py
ambient_backend_api_client/api/clusters_api.py
ambient_backend_api_client/api/commands_api.py
ambient_backend_api_client/api/health_api.py
ambient_backend_api_client/api/nodes_api.py
ambient_backend_api_client/api/notifications_api.py
ambient_backend_api_client/api/oauth_api.py
ambient_backend_api_client/api/ping_api.py
ambient_backend_api_client/api/registries_api.py
ambient_backend_api_client/api/requests_api.py
ambient_backend_api_client/api/services_api.py
ambient_backend_api_client/api/unimplemented_api.py
ambient_backend_api_client/api/upgrade_software_api.py
ambient_backend_api_client/api/users_api.py
ambient_backend_api_client/models/__init__.py
ambient_backend_api_client/models/account_type.py
ambient_backend_api_client/models/ambient_action_enum.py
ambient_backend_api_client/models/ambient_event_type_enum.py
ambient_backend_api_client/models/app_api_models_auth0_token_response.py
ambient_backend_api_client/models/app_api_models_cluster_status_enum.py
ambient_backend_api_client/models/app_api_models_node_status_enum.py
ambient_backend_api_client/models/app_api_models_token_token_response.py
ambient_backend_api_client/models/app_version.py
ambient_backend_api_client/models/architecture_enum.py
ambient_backend_api_client/models/aud.py
ambient_backend_api_client/models/auth0_device_code_response.py
ambient_backend_api_client/models/client_secret.py
ambient_backend_api_client/models/cluster.py
ambient_backend_api_client/models/cluster_create.py
ambient_backend_api_client/models/cluster_run_type.py
ambient_backend_api_client/models/cluster_select_options.py
ambient_backend_api_client-3.0.1.dist-info/METADATA
ambient_backend_api_client-3.0.1.dist-info/WHEEL
ambient_backend_api_client-3.0.1.dist-info/top_level.txt
ambient_backend_api_client-3.0.1.dist-info/RECORD
