Metadata-Version: 2.1
Name: ambient-backend-api-client
Version: 3.0.1
Summary: FastAPI
Home-page: 
Author: Ambient Labs Computing
Author-email: jose@ambientlabscomputing.com
Keywords: OpenAPI,OpenAPI-Generator,FastAPI
Requires-Dist: urllib3<3.0.1,>=1.25.3
Requires-Dist: python-dateutil
Requires-Dist: aiohttp>=3.0.1
Requires-Dist: aiohttp-retry>=2.8.3
Requires-Dist: pydantic>=2
Requires-Dist: typing-extensions>=4.7.1
